pycalima/Calima.py
pycalima/__init__.py
pycalima/cmdline.py
Calima-2.0.2.dist-info/LICENSE
Calima-2.0.2.dist-info/METADATA
Calima-2.0.2.dist-info/WHEEL
Calima-2.0.2.dist-info/entry_points.txt
Calima-2.0.2.dist-info/top_level.txt
Calima-2.0.2.dist-info/RECORD
