Metadata-Version: 2.1
Name: Calima
Version: 2.0.2
Summary: Python interface for Pax Calima Fan
Home-page: https://github.com/timutta/pycalima
Author: Timo Mutta
Author-email: unknown@unknown.com
License: Apache 2.0
Keywords: pax calima fan bluetooth ble
Platform: UNKNOWN
License-File: LICENSE
Requires-Dist: bluepy
